pitch/__init__.py
pitch/__main__.py
pitch/pitch.py
pitch/rate_limiter.py
pitch/setup.py
pitch/abstractions/__init__.py
pitch/abstractions/cloud_provider.py
pitch/configuration/__init__.py
pitch/configuration/pitch_config.py
pitch/models/__init__.py
pitch/models/json_serialize.py
pitch/models/tilt_status.py
pitch/providers/__init__.py
pitch/providers/azure_iothub.py
pitch/providers/brewersfriend_custom_stream.py
pitch/providers/brewfather_custom_stream.py
pitch/providers/calibration.py
pitch/providers/file.py
pitch/providers/grainfather_custom_stream.py
pitch/providers/influxdb.py
pitch/providers/influxdb2.py
pitch/providers/prometheus.py
pitch/providers/taplistio_custom_stream.py
pitch/providers/webhook.py
test/__init__.py
test/test_tilt_status.py
tilt_pitch-1.1.0.dist-info/LICENSE
tilt_pitch-1.1.0.dist-info/METADATA
tilt_pitch-1.1.0.dist-info/WHEEL
tilt_pitch-1.1.0.dist-info/top_level.txt
tilt_pitch-1.1.0.dist-info/RECORD
