Metadata-Version: 2.1
Name: tilt-pitch
Version: 1.1.0
Summary: Simple replacement for the Tilt Hydrometer mobile apps and TiltPi with lots of features
Home-page: https://github.com/linjmeyer/tilt-pitch/
Author: Lin Meyer
Author-email: lin@linmeyer.net
License: UNKNOWN
Platform: UNKNOWN
Classifier: Programming Language :: Python :: 3
Classifier: License :: OSI Approved :: GNU General Public License v3 (GPLv3)
Classifier: Operating System :: POSIX :: Linux
Requires-Python: >=3.7
License-File: LICENSE
Requires-Dist: prometheus-client
Requires-Dist: jsonpickle
Requires-Dist: python-interface
Requires-Dist: pyfiglet <1
Requires-Dist: influxdb
Requires-Dist: influxdb-client[ciso]
Requires-Dist: beacontools[scan]
Requires-Dist: azure-iot-device ==3.0.0b2
Requires-Dist: pybluez
